model_training_api_sagemaker/model_training_api_sagemaker.py
aissemble_extensions_model_training_api_sagemaker-1.9.4.dist-info/LICENSE
aissemble_extensions_model_training_api_sagemaker-1.9.4.dist-info/METADATA
aissemble_extensions_model_training_api_sagemaker-1.9.4.dist-info/WHEEL
aissemble_extensions_model_training_api_sagemaker-1.9.4.dist-info/RECORD
