Metadata-Version: 2.1
Name: aissemble-extensions-model-training-api-sagemaker
Version: 1.9.4
Summary: 
Author: aiSSEMBLE Baseline Community
Author-email: aissemble@bah.com
Requires-Python: >=3.11.4,<3.12
Classifier: Programming Language :: Python :: 3
Requires-Dist: fastapi (>=0.95.0)
Requires-Dist: krausening (>=19)
Requires-Dist: kubernetes (>=26.1.0)
Requires-Dist: mlflow (>=2.3.1,<3.0.0)
Requires-Dist: pydantic (>=2.8.0)
Requires-Dist: sagemaker (>=2.218.0)
Requires-Dist: urllib3 (>=1.26.18,<2.0.0)
Requires-Dist: uvicorn[standard] (>=0.18.0,<0.19.0)
